bokit/__init__.py
bokit/commands/ChatGPT.py
bokit/commands/CreateFlashcards.py
bokit/commands/DictionaryLookup.py
bokit/commands/OCR.py
bokit/commands/Phonetize.py
bokit/commands/TokenStatistics.py
bokit/commands/Tokenize.py
bokit/commands/Transifex.py
bokit/commands/Translate.py
bokit/commands/__init__.py
bokit/utils/__init__.py
bokit/utils/clean_tibetan_string.py
bokit/utils/create_particles_list.py
bokit/utils/create_punctuation_list.py
bokit/utils/create_special_char_list.py
bokit/utils/create_stopword_list.py
bokit/utils/is_all_latin.py
bokit/utils/is_all_tibetan.py
bokit/utils/is_partly_tibetan.py
bokit/utils/pdf_to_image.py
bokit/utils/read_text_from_file.py
bokit/utils/remove_non_tibetan.py
bokit/utils/tibetan_to_wylie.py
bokit/utils/wylie_to_tibetan.py
bokit/workflows/__init__.py
bokit/workflows/build_text.py
bokit/workflows/image_to_translation.py
bokit/workflows/pdf_to_translation.py
Bokit-0.2.3.dist-info/METADATA
Bokit-0.2.3.dist-info/WHEEL
Bokit-0.2.3.dist-info/top_level.txt
Bokit-0.2.3.dist-info/RECORD
